explainable_exceptions/__init__.py
explainable_exceptions/_modidx.py
explainable_exceptions/core.py
explainable_exceptions-1.0.2.dist-info/LICENSE
explainable_exceptions-1.0.2.dist-info/METADATA
explainable_exceptions-1.0.2.dist-info/WHEEL
explainable_exceptions-1.0.2.dist-info/entry_points.txt
explainable_exceptions-1.0.2.dist-info/top_level.txt
explainable_exceptions-1.0.2.dist-info/RECORD
