Metadata-Version: 2.1
Name: explainable-exceptions
Version: 1.0.2
Summary: A Python module to explain exceptions in execution-time using a magic cell
Home-page: https://github.com/ruescog/explainable-exceptions
Author: ruescog
Author-email: ruescog@unirioja.es
License: Apache Software License 2.0
Keywords: nbdev jupyter notebook python
Platform: UNKNOWN
Classifier: Development Status :: 4 - Beta
Classifier: Intended Audience :: Developers
Classifier: Natural Language :: English
Classifier: Programming Language :: Python :: 3.7
Classifier: Programming Language :: Python :: 3.8
Classifier: Programming Language :: Python :: 3.9
Classifier: Programming Language :: Python :: 3.10
Classifier: License :: OSI Approved :: Apache Software License
Requires-Python: >=3.7
Requires-Dist: hugchat
Provides-Extra: dev
